{
    "name": "Allen-Bradley-Azure",
    "labels": [],
    "deviceResources": [
        {
            "name": "test_dint",
            "description": "Double Int value",
            "attributes": {
                "type": "logixTag",
                "tagName": "test_dint"
            },
            "properties": {
                "valueType": "Int32",
                "readWrite": "R"
            }
        },
        {
            "name": "test_bool",
            "description": "Boolean Value",
            "attributes": {
                "type": "logixTag",
                "tagName": "test_bool"
            },
            "properties": {
                "valueType": "Bool",
                "readWrite": "R"
            }
        },
        {
            "name": "test_sint",
            "description": "Small Int value",
            "attributes": {
                "type": "logixTag",
                "tagName": "test_sint"
            },
            "properties": {
                "valueType": "Int8",
                "readWrite": "R"
            }
        },
        {
            "name": "test_real",
            "description": "Floating point value",
            "attributes": {
                "type": "logixTag",
                "tagName": "test_real"
            },
            "properties": {
                "valueType": "Float32",
                "readWrite": "R"
            }
        },
        {
            "name": "test_string",
            "description": "String Value",
            "attributes": {
                "type": "logixTag",
                "tagName": "test_string"
            },
            "properties": {
                "valueType": "String",
                "readWrite": "R"
            }
        },
        {
            "name": "test_int",
            "description": "String Value",
            "attributes": {
                "type": "logixTag",
                "tagName": "test_int"
            },
            "properties": {
                "valueType": "Int16",
                "readWrite": "R"
            }
        },
        {
            "name": "Local:1:O.Data",
            "description": "Local:1:O output data",
            "attributes": {
                "type": "logixTag",
                "tagName": "Local:1:O.Data"
            },
            "properties": {
                "valueType": "Uint8Array",
                "readWrite": "R"
            }
        }
    ]
}