{
    "name": "Allen-Bradley-Azure",
    "labels": [],
    "deviceResources": [
        {
            "name": "DINT_ARRAY",
            "properties": {
                "value": {
                    "type": "Uint8Array",
                    "readWrite": "R"
                },
                "units": {
                    "type": "String",
                    "readWrite": "R"
                }
            },
            "attributes": {
                "tagName": "DINT_ARRAY",
                "type": "logixTag"
            }
        },
        {
            "name": "DINT_ARRAY[0]",
            "properties": {
                "value": {
                    "type": "Int32",
                    "readWrite": "R"
                },
                "units": {
                    "type": "String",
                    "readWrite": "R"
                }
            },
            "attributes": {
                "tagName": "DINT_ARRAY[0]",
                "type": "logixTag"
            }
        },
        {
            "name": "DINT_ARRAY[1]",
            "properties": {
                "value": {
                    "type": "Int32",
                    "readWrite": "R"
                },
                "units": {
                    "type": "String",
                    "readWrite": "R"
                }
            },
            "attributes": {
                "tagName": "DINT_ARRAY[1]",
                "type": "logixTag"
            }
        },
        {
            "name": "DINT_ARRAY[2]",
            "properties": {
                "value": {
                    "type": "Int32",
                    "readWrite": "R"
                },
                "units": {
                    "type": "String",
                    "readWrite": "R"
                }
            },
            "attributes": {
                "tagName": "DINT_ARRAY[2]",
                "type": "logixTag"
            }
        },
        {
            "name": "DINT_ARRAY[3]",
            "properties": {
                "value": {
                    "type": "Int32",
                    "readWrite": "R"
                },
                "units": {
                    "type": "String",
                    "readWrite": "R"
                }
            },
            "attributes": {
                "tagName": "DINT_ARRAY[3]",
                "type": "logixTag"
            }
        },
        {
            "name": "DINT_ARRAY[4]",
            "properties": {
                "value": {
                    "type": "Int32",
                    "readWrite": "R"
                },
                "units": {
                    "type": "String",
                    "readWrite": "R"
                }
            },
            "attributes": {
                "tagName": "DINT_ARRAY[4]",
                "type": "logixTag"
            }
        },
        {
            "name": "DINT_ARRAY[5]",
            "properties": {
                "value": {
                    "type": "Int32",
                    "readWrite": "R"
                },
                "units": {
                    "type": "String",
                    "readWrite": "R"
                }
            },
            "attributes": {
                "tagName": "DINT_ARRAY[5]",
                "type": "logixTag"
            }
        },
        {
            "name": "DINT_ARRAY[6]",
            "properties": {
                "value": {
                    "type": "Int32",
                    "readWrite": "R"
                },
                "units": {
                    "type": "String",
                    "readWrite": "R"
                }
            },
            "attributes": {
                "tagName": "DINT_ARRAY[6]",
                "type": "logixTag"
            }
        },
        {
            "name": "DINT_ARRAY[7]",
            "properties": {
                "value": {
                    "type": "Int32",
                    "readWrite": "R"
                },
                "units": {
                    "type": "String",
                    "readWrite": "R"
                }
            },
            "attributes": {
                "tagName": "DINT_ARRAY[7]",
                "type": "logixTag"
            }
        },
        {
            "name": "DINT_ARRAY[8]",
            "properties": {
                "value": {
                    "type": "Int32",
                    "readWrite": "R"
                },
                "units": {
                    "type": "String",
                    "readWrite": "R"
                }
            },
            "attributes": {
                "tagName": "DINT_ARRAY[8]",
                "type": "logixTag"
            }
        },
        {
            "name": "DINT_ARRAY[9]",
            "properties": {
                "value": {
                    "type": "Int32",
                    "readWrite": "R"
                },
                "units": {
                    "type": "String",
                    "readWrite": "R"
                }
            },
            "attributes": {
                "tagName": "DINT_ARRAY[9]",
                "type": "logixTag"
            }
        },
        {
            "name": "DINT_ARRAY[10]",
            "properties": {
                "value": {
                    "type": "Int32",
                    "readWrite": "R"
                },
                "units": {
                    "type": "String",
                    "readWrite": "R"
                }
            },
            "attributes": {
                "tagName": "DINT_ARRAY[10]",
                "type": "logixTag"
            }
        },
        {
            "name": "DINT_ARRAY[11]",
            "properties": {
                "value": {
                    "type": "Int32",
                    "readWrite": "R"
                },
                "units": {
                    "type": "String",
                    "readWrite": "R"
                }
            },
            "attributes": {
                "tagName": "DINT_ARRAY[11]",
                "type": "logixTag"
            }
        }
    ]
}